daspro/__init__.py
daspro/kel3.py
Kelompok3-0.0.1.dist-info/LICENSE
Kelompok3-0.0.1.dist-info/METADATA
Kelompok3-0.0.1.dist-info/WHEEL
Kelompok3-0.0.1.dist-info/top_level.txt
Kelompok3-0.0.1.dist-info/RECORD
