Metadata-Version: 2.1
Name: Kelompok3
Version: 0.0.1
Summary: Tubes
Home-page: https://github.com/SeladaKeju/Kelompok3
Author: SeladaKeju
Author-email: <rizqiadit2430@gmail.com>
License: MIT
Keywords: Tubes
Classifier: Development Status :: 1 - Planning
License-File: LICENSE
